madliar/__init__.py
madliar/core.py
madliar/exceptions.py
madliar/management.py
madliar/template.py
madliar/utils.py
madliar/config/__init__.py
madliar/config/log4.py
madliar/config/project_template.py
madliar/http/__init__.py
madliar/http/middleware.py
madliar/http/request.py
madliar/http/response.py
madliar-0.1a1.dev1259.dist-info/DESCRIPTION.rst
madliar-0.1a1.dev1259.dist-info/METADATA
madliar-0.1a1.dev1259.dist-info/RECORD
madliar-0.1a1.dev1259.dist-info/WHEEL
madliar-0.1a1.dev1259.dist-info/entry_points.txt
madliar-0.1a1.dev1259.dist-info/metadata.json
madliar-0.1a1.dev1259.dist-info/top_level.txt
madliar-0.1a1.dev1259.dist-info/zip-safe
