Metadata-Version: 2.0
Name: madliar
Version: 0.1a1.dev1259
Summary: A tiny WSGI freamwork.
Home-page: https://github.com/cl-ei
Author: caoliang
Author-email: i@caoliang.net
License: MIT
Platform: UNKNOWN
Classifier: License :: OSI Approved :: MIT License
Classifier: Intended Audience :: Developers
Classifier: Operating System :: OS Independent
Classifier: Programming Language :: Python :: 2
Classifier: Programming Language :: Python :: 2.6
Classifier: Programming Language :: Python :: 2.7
